pikantic/__init__.py
pikantic-0.1.2.dist-info/LICENSE
pikantic-0.1.2.dist-info/WHEEL
pikantic-0.1.2.dist-info/METADATA
pikantic-0.1.2.dist-info/RECORD
