Metadata-Version: 2.1
Name: pikantic
Version: 0.1.2
Summary: Python library for easy message broker handling using Pydantic
Home-page: https://github.com/tomgrin10/pikantic
License: MIT
Keywords: pika,rabbitmq,amqp,pydantic,fastapi,rabbit,mq
Author: Tom Gringauz
Author-email: tomgrin10@gmail.com
Requires-Python: >=3.7,<4.0
Classifier: Development Status :: 3 - Alpha
Classifier: Intended Audience :: Developers
Classifier: License :: OSI Approved :: MIT License
Classifier: Programming Language :: Python :: 3
Classifier: Programming Language :: Python :: 3.7
Classifier: Programming Language :: Python :: 3.8
Classifier: Programming Language :: Python :: 3.9
Classifier: Topic :: Utilities
Classifier: Typing :: Typed
Requires-Dist: aio-pika (>=6.8.0,<7.0.0)
Requires-Dist: pydantic (>=1.8.2,<2.0.0)
Project-URL: Repository, https://github.com/tomgrin10/pikantic
